LICENSE
MANIFEST.in
README.md
pyproject.toml
setup.cfg
setup.py
selph_light_lib/__init__.py
selph_light_lib/color.py
selph_light_lib/const.py
selph_light_lib/info.py
selph_light_lib/wave.py
selph_light_lib.egg-info/PKG-INFO
selph_light_lib.egg-info/SOURCES.txt
selph_light_lib.egg-info/dependency_links.txt
selph_light_lib.egg-info/not-zip-safe
selph_light_lib.egg-info/top_level.txt
src/extension.c
src/wave/wave_module.c
src/wave/wave_module.h
src/wave/components/cie_rgb.c
src/wave/components/cie_rgb.h